gigaml_secrets/__init__.py
gigaml_secrets/aws_secrets_manager.py
gigaml_secrets/secrets_manager.py
gigaml_secrets-0.50.dist-info/METADATA
gigaml_secrets-0.50.dist-info/WHEEL
gigaml_secrets-0.50.dist-info/top_level.txt
gigaml_secrets-0.50.dist-info/RECORD
